particlespell/__init__.py
particlespell/particle_variants.json
particlespell/particlespell.py
particlespell-0.0.2.dist-info/METADATA
particlespell-0.0.2.dist-info/WHEEL
particlespell-0.0.2.dist-info/licenses/LICENSE
particlespell-0.0.2.dist-info/RECORD
