Metadata-Version: 2.4
Name: particlespell
Version: 0.0.2
Summary: PDG-powered particle data tool with multi-name variant support
Author-email: zhangbolun <zhangbolun@ihep.ac.cn>
License-Expression: MIT
License-File: LICENSE
Classifier: Intended Audience :: Science/Research
Classifier: License :: OSI Approved :: MIT License
Classifier: Operating System :: OS Independent
Classifier: Programming Language :: Python :: 3.12
Classifier: Topic :: Scientific/Engineering :: Physics
Requires-Python: >=3.12
Requires-Dist: particle>=0.25.3
Requires-Dist: pdg>=0.1.4
